pesto_orm/__init__.py
pesto_orm/core/__init__.py
pesto_orm/core/base.py
pesto_orm/core/error.py
pesto_orm/core/executor.py
pesto_orm/core/model.py
pesto_orm/core/repository.py
pesto_orm/db/__init__.py
pesto_orm/db/connection.py
pesto_orm/db/pool.py
pesto_orm/dialect/__init__.py
pesto_orm/dialect/base.py
pesto_orm/dialect/mysql/__init__.py
pesto_orm/dialect/mysql/domain.py
pesto_orm/dialect/mysql/record.py
pesto_orm/pipeline/__init__.py
pesto_orm/pipeline/repository.py
pesto_orm-0.0.7.dist-info/METADATA
pesto_orm-0.0.7.dist-info/WHEEL
pesto_orm-0.0.7.dist-info/top_level.txt
pesto_orm-0.0.7.dist-info/RECORD
