Metadata-Version: 2.1
Name: pesto-orm
Version: 0.0.7
Summary: Minimalist python-orm framework
Home-page: https://github.com/Dreampie/pesto
Author: Dreampie
Author-email: Dreampie@outlook.com
License: UNKNOWN
Keywords: minimalist,python,mysql,orm,pesto
Platform: all
Requires-Dist: pesto-common (==0.0.6)
